dns_smtp_email_validator/__init__.py
dns_smtp_email_validator/main.py
dns_smtp_email_validator-0.1.12.dist-info/licenses/LICENSE
tests/__init__.py
tests/test.py
dns_smtp_email_validator-0.1.12.dist-info/METADATA
dns_smtp_email_validator-0.1.12.dist-info/WHEEL
dns_smtp_email_validator-0.1.12.dist-info/top_level.txt
dns_smtp_email_validator-0.1.12.dist-info/RECORD
