Metadata-Version: 2.4
Name: dns-smtp-email-validator
Version: 0.1.12
Summary: DNS and SMTP Email Validator is a robust Python library designed
Author-email: shailesh pandit <shaileshpandit141@gmail.com>
License: MIT License
Project-URL: Homepage, https://github.com/shaileshpandit141/dns-smtp-email-validator
Project-URL: Repository, https://github.com/shaileshpandit141/dns-smtp-email-validator
Classifier: Programming Language :: Python :: 3
Classifier: License :: OSI Approved :: MIT License
Classifier: Operating System :: OS Independent
Requires-Python: >=3.10
License-File: LICENSE
Requires-Dist: dnspython>=2.3.0
Requires-Dist: load-dotenv>=0.1.0
Dynamic: license-file
